mrcedee_myormsql/sales.py
mrcedee_myormsql/settings.py
mysq_orm-0.0.1.dist-info/METADATA
mysq_orm-0.0.1.dist-info/WHEEL
mysq_orm-0.0.1.dist-info/licenses/LICENSE
mysq_orm-0.0.1.dist-info/RECORD
