Metadata-Version: 2.1
Name: mysq_orm
Version: 0.0.1
Summary: My customized ORM on Sales
Project-URL: Homepage, https://github.com/MrCedee/mysq_orm
Project-URL: Bug Tracker, https://github.com/MrCedee/mysq_orm/issues
Author-email: MrCedee <marcoscedenillabonet@gmail.com>
License:                                  Apache License
License-File: LICENSE
Classifier: License :: OSI Approved :: MIT License
Classifier: Operating System :: OS Independent
Classifier: Programming Language :: Python :: 3
Requires-Python: >=3.9
